LICENSE
MANIFEST.in
README.md
setup.py
apps/urls.txt
apps/wayback_crawler.py
apps/wayback_retriever.py
libwayback/__init__.py
libwayback/crawler.py
libwayback/retriever.py
libwayback.egg-info/PKG-INFO
libwayback.egg-info/SOURCES.txt
libwayback.egg-info/dependency_links.txt
libwayback.egg-info/top_level.txt