Metadata-Version: 1.0
Name: libwayback
Version: 1.0
Summary: A library to parse Wayback Machine of archive.org to get a historical views of web pages.
Home-page: https://github.com/caesar0301/libwayback
Author: Jamin Chen
Author-email: chenxm35@gmail.com
License: LICENSE
Platform: UNKNOWN
Classifier: Development Status :: 4 - Beta
Classifier: Environment :: Console
Classifier: Intended Audience :: Developers
Classifier: License :: Freely Distributable
Classifier: Operating System :: OS Independent
Classifier: Programming Language :: Python
Classifier: Programming Language :: Python :: 2.6
Classifier: Programming Language :: Python :: 2.7
Classifier: Topic :: Software Development :: Libraries :: Python Modules
